<?xml version = '1.0' encoding = 'UTF-8'?>
<Diagram class="oracle.dbtools.crest.swingui.logical.DPVLogicalSubView" name="Logical - SubView_1" id="F9A00EE7-6CF8-5164-A4D9-92594D55D70C">
<createdBy>gpallares</createdBy>
<modifiedBy>gpallares</modifiedBy>
<createdTime>2016-02-22 19:10:28 UTC</createdTime>
<autoRoute>false</autoRoute>
<boxInbox>true</boxInbox>
<showLegend>false</showLegend>
<showLabels>false</showLabels>
<showRelAttributes>false</showRelAttributes>
<gridEnabled>false</gridEnabled>
<showGrid>false</showGrid>
<diagramColor>-1</diagramColor>
<display>false</display>
<notation>1</notation>
</Diagram>